[{"time-profiles":[{"probability":5.0,"profile":[{"duration":{"start-time":["08:00:00","00:10:00"],"end-time":["18:00:00","00:10:00"],"required":["05:00:00","01:00:00"]},"pattern":{"end-date":"2018-03-02","period":"week","period-details":{"days-of-week":[1,3,5]},"start-date":"2018-02-12"}}]},{"probability":2.0,"profile":[{"duration":{"start-time":["08:00:00","00:10:00"],"end-time":["18:00:00","00:10:00"],"required":["05:00:00","01:00:00"]},"pattern":{"end-date":"2018-03-02","period":"week","period-details":{"days-of-week":[2,4]},"start-date":"2018-02-12"}}]}],"probability":10.0,"description":"Worker A","id":1,"event-affinity":[{"metaevent-id":1,"probability":10.0},{"metaevent-id":2,"probability":5.0},{"metaevent-id":3,"probability":2.0},{"metaevent-id":4,"probability":2.0}]},{"time-profiles":[{"probability":5.0,"profile":[{"duration":{"start-time":["08:00:00","00:10:00"],"end-time":["18:00:00","00:10:00"],"required":["05:00:00","01:00:00"]},"pattern":{"end-date":"2018-03-02","period":"week","period-details":{"days-of-week":[2,4]},"start-date":"2018-02-12"}}]},{"probability":2.0,"profile":[{"duration":{"start-time":["08:00:00","00:10:00"],"end-time":["18:00:00","00:10:00"],"required":["05:00:00","01:00:00"]},"pattern":{"end-date":"2018-03-02","period":"week","period-details":{"days-of-week":[1,3,5]},"start-date":"2018-02-12"}}]}],"probability":10.0,"description":"Worker B","id":2,"event-affinity":[{"metaevent-id":1,"probability":5.0},{"metaevent-id":2,"probability":10.0},{"metaevent-id":3,"probability":2.0},{"metaevent-id":4,"probability":2.0}]}]